mhjsmap/__init__.py
mhjsmap/mcpmap.py
mhjsmap-1.1.3.dist-info/METADATA
mhjsmap-1.1.3.dist-info/WHEEL
mhjsmap-1.1.3.dist-info/entry_points.txt
mhjsmap-1.1.3.dist-info/top_level.txt
mhjsmap-1.1.3.dist-info/RECORD
